plover_cycle_translations/__init__.py
plover_cycle_translations/extension.py
plover_cycle_translations/translation/__init__.py
plover_cycle_translations/translation/cycle.py
plover_cycle_translations/translation/list.py
plover_cycle_translations-0.5.4.dist-info/LICENSE.txt
plover_cycle_translations-0.5.4.dist-info/METADATA
plover_cycle_translations-0.5.4.dist-info/WHEEL
plover_cycle_translations-0.5.4.dist-info/entry_points.txt
plover_cycle_translations-0.5.4.dist-info/top_level.txt
plover_cycle_translations-0.5.4.dist-info/zip-safe
plover_cycle_translations-0.5.4.dist-info/RECORD
