Metadata-Version: 2.1
Name: plover_cycle_translations
Version: 0.5.4
Summary: Define multiple translations in a single steno outline and cycle through them.
Home-page: https://github.com/paulfioravanti/plover-cycle-translations
Author: Paul Fioravanti
Author-email: paul@paulfioravanti.com
License: GNU General Public License v3 or later (GPLv3+)
Keywords: plover plover_plugin
Classifier: Development Status :: 4 - Beta
Classifier: Environment :: Plugins
Classifier: Intended Audience :: End Users/Desktop
Classifier: Operating System :: OS Independent
Classifier: Programming Language :: Python :: 3
Classifier: Programming Language :: Python :: 3.9
License-File: LICENSE.txt
Requires-Dist: plover >=4.0.0.dev12
Provides-Extra: test
Requires-Dist: coverage ; extra == 'test'
Requires-Dist: mypy ; extra == 'test'
Requires-Dist: pylint ; extra == 'test'
Requires-Dist: pytest ; extra == 'test'
Requires-Dist: pytest-cov ; extra == 'test'
